crabby/__init__.py
crabby/__version__.py
crabby/detect.py
crabby/guiapp.py
crabby/modzscore.py
crabby/stimcalc.py
crabby/io/__init__.py
crabby/io/load.py
crabby/io/readcrabanalyzer.py
crabby/model/__init__.py
crabby/model/neuronparameters.py
crabby/plot/__init__.py
crabby/plot/crabanalyzerplotting.py
crabby/plot/matplotlibmisc.py
crabby/plot/scrollabletimeseries.py
crabby-0.0.2.dist-info/METADATA
crabby-0.0.2.dist-info/WHEEL
crabby-0.0.2.dist-info/top_level.txt
crabby-0.0.2.dist-info/RECORD
