Metadata-Version: 2.1
Name: crabby
Version: 0.0.2
Summary: A collection of scripts used in the Nusbaum Lab for data analysis, modeling, and visualization
Home-page: https://github.com/LoganJF/crabby
Author: Logan Fickling
Author-email: loganfickling@gmail.com
License: UNKNOWN
Platform: UNKNOWN
Requires-Python: >=3.6.0
Requires-Dist: scipy
Requires-Dist: numpy
Requires-Dist: pandas
Requires-Dist: matplotlib
Requires-Dist: seaborn
Requires-Dist: pandastable
Requires-Dist: brian2
Requires-Dist: neo
